{
  "response": {
    "model_version": "popularity_v1",
    "items": [
      {
        "item_id": "item_0005",
        "score": 0.37316143571768723,
        "reasons": [
          "recent_popularity",
          "co_visitation",
          "diversity",
          "personalization",
          "rule.pin[c1e2a5c6-9f9c-453d-93fe-6bf0ae6da86c]"
        ]
      },
      {
        "item_id": "item_0209",
        "score": 0.8719054981897169,
        "reasons": [
          "recent_popularity",
          "content_similarity",
          "co_visitation",
          "embedding_similarity",
          "diversity",
          "personalization"
        ]
      },
      {
        "item_id": "item_0101",
        "score": 0.7518253112755707,
        "reasons": [
          "recent_popularity",
          "content_similarity",
          "co_visitation",
          "embedding_similarity",
          "diversity",
          "personalization"
        ]
      },
      {
        "item_id": "item_0003",
        "score": 0.6738039050615622,
        "reasons": [
          "recent_popularity",
          "content_similarity",
          "co_visitation",
          "embedding_similarity",
          "diversity",
          "personalization"
        ]
      },
      {
        "item_id": "item_0275",
        "score": 0.6117076384657963,
        "reasons": [
          "recent_popularity",
          "content_similarity",
          "embedding_similarity",
          "diversity",
          "personalization"
        ]
      },
      {
        "item_id": "item_0037",
        "score": 0.6002446546789425,
        "reasons": [
          "recent_popularity",
          "content_similarity",
          "co_visitation",
          "embedding_similarity",
          "diversity",
          "personalization"
        ]
      },
      {
        "item_id": "item_0001",
        "score": 0.48237083071151227,
        "reasons": [
          "recent_popularity",
          "co_visitation",
          "diversity",
          "personalization"
        ]
      },
      {
        "item_id": "item_0142",
        "score": 0.1379757519176085,
        "reasons": [
          "recent_popularity",
          "co_visitation",
          "diversity"
        ]
      },
      {
        "item_id": "item_0092",
        "score": 0.1199527597272383,
        "reasons": [
          "recent_popularity",
          "co_visitation",
          "diversity",
          "personalization"
        ]
      },
      {
        "item_id": "item_0057",
        "score": 0.09646651856704548,
        "reasons": [
          "recent_popularity",
          "co_visitation",
          "diversity"
        ]
      }
    ],
    "trace": {
      "extras": {
        "candidate_sources": {
          "collaborative": {
            "count": 0,
            "duration_ms": 0.117875
          },
          "content": {
            "count": 20,
            "duration_ms": 1.921323
          },
          "merged": {
            "count": 320,
            "duration_ms": 0.017353
          },
          "popularity": {
            "count": 300,
            "duration_ms": 11.302276
          },
          "post_exclusion": {
            "count": 320,
            "duration_ms": 1.547598
          },
          "session": {
            "count": 0,
            "duration_ms": 0.271158
          }
        },
        "policy": {
          "total_candidates": 320,
          "explicit_exclude_hits": 0,
          "recent_event_exclude_hits": 0,
          "after_exclusions": 320,
          "constraint_filtered_count": 0,
          "after_constraint_filters": 320,
          "rule_block_count": 0,
          "rule_pin_count": 1,
          "rule_boost_count": 0,
          "rule_boost_injected": 0,
          "rule_boost_exposure": 0,
          "rule_pin_exposure": 1,
          "after_rules": 319,
          "final_count": 10,
          "constraint_leak_count": 0
        }
      }
    }
  },
  "target_item": "item_0005",
  "rank": 0,
  "rule": {
    "rule_id": "c1e2a5c6-9f9c-453d-93fe-6bf0ae6da86c",
    "namespace": "default",
    "surface": "home",
    "name": "scenario_s5_pin_item",
    "description": "Scenario S5 pin position test",
    "action": "PIN",
    "target_type": "ITEM",
    "item_ids": [
      "item_0005"
    ],
    "max_pins": 1,
    "priority": 200,
    "enabled": true,
    "created_at": "2025-11-03T19:00:26Z",
    "updated_at": "2025-11-03T19:00:26Z"
  }
}